odlclient/__init__.py
odlclient/client.py
odlclient/cmdutils.py
odlclient/main.py
odlclient/tests/__init__.py
python_odlclient-0.0.1.dist-info/DESCRIPTION.rst
python_odlclient-0.0.1.dist-info/METADATA
python_odlclient-0.0.1.dist-info/RECORD
python_odlclient-0.0.1.dist-info/WHEEL
python_odlclient-0.0.1.dist-info/entry_points.txt
python_odlclient-0.0.1.dist-info/metadata.json
python_odlclient-0.0.1.dist-info/pbr.json
python_odlclient-0.0.1.dist-info/top_level.txt
