Metadata-Version: 2.0
Name: python-odlclient
Version: 0.0.1
Summary: OpenDaylight Client Library and Command
Home-page: https://github.com/yuuichi-fujioka/python-odlclient
Author: Yuuichi Fujioka
Author-email: fujioka.yuuichi@gmail.com
License: Apache License, Version 2.0
Platform: UNKNOWN
Classifier: Intended Audience :: Information Technology
Classifier: Intended Audience :: System Administrators
Classifier: License :: OSI Approved :: Apache Software License
Classifier: Operating System :: POSIX :: Linux
Classifier: Programming Language :: Python
Classifier: Programming Language :: Python :: 2
Classifier: Programming Language :: Python :: 2.7
Requires-Dist: PrettyTable
Requires-Dist: click
Requires-Dist: requests
Requires-Dist: six
Requires-Dist: xmltodict
